x_tools/mypy/__init__.py
x_tools/mypy/main_mypy.py
x_tools_mypy-0.2.0.dist-info/METADATA
x_tools_mypy-0.2.0.dist-info/WHEEL
x_tools_mypy-0.2.0.dist-info/entry_points.txt
x_tools_mypy-0.2.0.dist-info/top_level.txt
x_tools_mypy-0.2.0.dist-info/RECORD
