Metadata-Version: 2.4
Name: x_tools-mypy
Version: 0.2.0
Summary: MyPy - Pomocný nástroj pro správu kódu
Author-email: Milan Brzoň <milan.brzon@generaliceska.cz>
Classifier: Programming Language :: Python :: 3
Classifier: Operating System :: OS Independent
Requires-Python: >=3.9
Requires-Dist: x_tools-utils~=0.2.0
Requires-Dist: mypy~=1.17.1
